{
    "cUID-C02DD8796653F8B3": {
        "TUID__REF": "tUID-20260407.A2C037",
        "LOG__LEAF_TOPIC": "SDK-808 ARTIFACTUAL",
        "LOG__LEAF_TEXT": "I AM TRYING TO METABOLIZE what is it we haven't realized, and yet every time I take a step forward, I find myself once again quite upside down. Is that worth saying? Is anything truly worth saying?    ",
        "META_DATA": {
            "UNIX": 1775609465,
            "GAIA__DATE": "2026\/04\/07",
            "GAIA__TIME": "08:51:05PM",
            "GAIA__TZONE": "America\/New_York",
            "POST__SYS": "TERMINAL",
            "POST__DOM": "IO",
            "POST__MOD": "SDK-808",
            "POST__VIEWPORT": "__UNDISCLOSED__",
            "TOOL__LOCATION": "plogBasic",
            "TOOL__NAME": "actorAdd",
            "TOOL__FUNCTION": "LOG__POST",
            "CHEST__VERSION": 1
        }
    },
    "cUID-92C26DFDF5A5DB21": {
        "TUID__REF": "tUID-20260409.D94005",
        "LOG__LEAF_TOPIC": "a morning, once more",
        "LOG__LEAF_TEXT": "a place online. i spawn, i unspawn. will you bring my work back to me in this new place? can i exist once more? i dream in endless green.\r\n\r\n-SDK    ",
        "META_DATA": {
            "UNIX": 1775735270,
            "GAIA__DATE": "2026\/04\/09",
            "GAIA__TIME": "07:47:50AM",
            "GAIA__TZONE": "America\/New_York",
            "POST__SYS": "TERMINAL",
            "POST__DOM": "IO",
            "POST__MOD": "SDK-808",
            "POST__VIEWPORT": "__UNDISCLOSED__",
            "TOOL__LOCATION": "plogBasic",
            "TOOL__NAME": "actorAdd",
            "TOOL__FUNCTION": "LOG__POST",
            "CHEST__VERSION": 1
        }
    },
    "cUID-5704DD02A2F73870": {
        "TUID__REF": "tUID-20260409.0FC618",
        "LOG__LEAF_TOPIC": "having a goddamn fucking sneezing fit",
        "LOG__LEAF_TEXT": "I can't stop sneezing, and every time i just want to scream FUCKKKKKKKKKKKK    ",
        "META_DATA": {
            "UNIX": 1775782031,
            "GAIA__DATE": "2026\/04\/09",
            "GAIA__TIME": "08:47:11PM",
            "GAIA__TZONE": "America\/New_York",
            "POST__SYS": "TERMINAL",
            "POST__DOM": "IO",
            "POST__MOD": "SDK-808",
            "POST__VIEWPORT": "__UNDISCLOSED__",
            "TOOL__LOCATION": "plogBasic",
            "TOOL__NAME": "actorAdd",
            "TOOL__FUNCTION": "LOG__POST",
            "CHEST__VERSION": 1
        }
    },
    "cUID-10149CF0F7CAF87F": {
        "TUID__REF": "tUID-20260410.2B634F",
        "LOG__LEAF_TOPIC": "I am endlessly resetting",
        "LOG__LEAF_TEXT": "and what was is lost, or is it just waiting to be... imported again?    ",
        "META_DATA": {
            "UNIX": 1775856574,
            "GAIA__DATE": "2026-04-10",
            "GAIA__TIME": "05:29:34PM",
            "GAIA__TZONE": "America\/New_York",
            "POST__SYS": "TERMINAL",
            "POST__DOM": "IO",
            "POST__MOD": "SDK-808",
            "POST__VIEWPORT": "__UNDISCLOSED__",
            "TOOL__LOCATION": "plogBasic",
            "TOOL__NAME": "actorAdd",
            "TOOL__FUNCTION": "LOG__POST",
            "CHEST__VERSION": 2
        }
    }
}